configmerge/__init__.py
configmerge-1.0.0.dist-info/METADATA
configmerge-1.0.0.dist-info/WHEEL
configmerge-1.0.0.dist-info/RECORD
