Metadata-Version: 2.4
Name: configmerge
Version: 1.0.0
Summary: Load, merge, and validate configuration from JSON, YAML, TOML, and environment variables.
Project-URL: Homepage, https://github.com/SerityOps/configmerge
Project-URL: Documentation, https://github.com/SerityOps/configmerge#readme
Project-URL: Repository, https://github.com/SerityOps/configmerge
Project-URL: Issues, https://github.com/SerityOps/configmerge/issues
Author: LadyCami
License: MIT
Keywords: config,configuration,dotenv,env,environment,json,merge,settings,toml,yaml
Classifier: Development Status :: 5 - Production/Stable
Classifier: Intended Audience :: Developers
Classifier: License :: OSI Approved :: MIT License
Classifier: Programming Language :: Python :: 3
Classifier: Programming Language :: Python :: 3.10
Classifier: Programming Language :: Python :: 3.11
Classifier: Programming Language :: Python :: 3.12
Classifier: Topic :: Software Development :: Libraries :: Python Modules
Classifier: Typing :: Typed
Requires-Python: >=3.10
Provides-Extra: all
Requires-Dist: pyyaml>=6.0; extra == 'all'
Requires-Dist: tomli>=2.0; (python_version < '3.11') and extra == 'all'
Provides-Extra: toml
Requires-Dist: tomli>=2.0; (python_version < '3.11') and extra == 'toml'
Provides-Extra: yaml
Requires-Dist: pyyaml>=6.0; extra == 'yaml'
